{
  "cocktails": [
    {
      "title": "paloma spritz",
      "description": "tequila blanco cazadores, licor de flor de saüc st. germain, llima, aranja, sour beer & soda.",
      "flavors": "floral, agradablement cítric. bombolles simpàtiques.",
      "price": 11,
      "al·lèrgens": "no conté"
    },
    {
      "title": "antonietta",
      "description": "vodka grey goose, coconut sherry.",
      "flavors": "refrescant, delicadament herbal i cítric, amb una subtil nota de coco, exòtic i bombollejant.",
      "price": 11,
      "alergenos": "no conté"
    },
    {
      "title": "cheesecake white negroni",
      "description": "martini bitter, vermut martini ambrato i noilly prat dry, ginebra bombay sapphire, infusió de cheesecake.",
      "flavors": "aromàtic i complex, amb amargors elegants, notes especiades i un final cremós i subtil que recorda un postre.",
      "price": 11,
      "alergenos": "no conté"
    },
    {
      "title": "bitter banana split",
      "description": "Whisky de sègol michter's, martini bitter, licor de plàtan i cacau.",
      "flavors": "intens i especiat, amb una amargor profunda, dolçor madura de plàtan i un tancament vellutat de cacau.",
      "price": 12,
      "alergenos": "no conté"
    },
    {
      "title": "philly vic punch",
      "description": "rom envellit santa teresa, préssec caramelitzat, porto vermell, licor de préssec, te de djarleig & llimona.",
      "flavors": "complex, dolç, delicadament aromatitzat.",
      "price": 12,
      "al·lèrgens": "no conté"
    },
    {
      "title": "after dark",
      "description": "tequila patrón blanco, aperitiu cocchi rosa, amaro montenegro, sorbet d'aranja, llimona.",
      "flavors": "brillant i cítric, amb capes amargues i dolces ben equilibrades, tocs florals i un final vibrant d'aranja.",
      "price": 13,
      "alergenos": "no conté"
    },
    {
      "title": "la última palabra",
      "description": "mezcal union, chartreuse verd, maraschino, llima, escuma de pinya & pebre vermell.",
      "flavors": "herbal, fumat & tropical.",
      "price": 12,
      "al·lèrgens": "no conté"
    },
    {
      "title": "lonely calling",
      "description": "ginebra condesa, barreja de xerès Lonely, llimona, sorbet de llimona i angostura bitter.",
      "flavors": "cítric i especiat, amb notes botàniques fresques, acidesa vibrant i un toc sec i aromàtic.",
      "price": 11,
      "alergenos": "no conté"
    },
    {
      "title": "closer to god",
      "description": "mezcal, aperitiu cocchi americano, vi blanc, sorbet de llimona, soda de camamilla salada.",
      "flavors": "fumat i cítric, amb frescor herbal i delicades notes salines, elegant i refrescant amb un final floral i sec.",
      "price": 12,
      "alergenos": "no conté"
    },
    {
      "title": "blueberry hill",
      "description": "rom bacardí blanc, vi palomino fi, llimona, melmelada de nabius, clara d'ou i pols de remolatxa.",
      "flavors": "àcid i afruitat amb textura sedosa, tocs secs i dolçor natural.",
      "price": 11,
      "alergenos": "conté ou"
    },
    {
      "title": "gin fino basil smash",
      "description": "bombay dry gin, vi de xerès fino, alfàbrega & llimona",
      "flavors": "fresc amb final intens",
      "price": 11,
      "al·lèrgens": "no conté"
    },
    {
      "title": "adonis sour",
      "description": "martini rubino, amontillado, sorbet de taronja i angostura bitter",
      "flavors": "un home de gran bellesa, humor àcid i un toc d’amargor: m’ho quedo",
      "price": 11,
      "al·lèrgens": "conté ou"
    },
    {
      "title": "lion's tail",
      "description": "whisky dewar's white label, bourbon i pimiento dram",
      "flavors": "aromàtic i especiat",
      "price": 11,
      "al·lèrgens": "no conté"
    },
    {
      "title": "gimlet penedès",
      "description": "gin bombay premier cru, cordial de cava i llimona",
      "flavors": "sutilesa i harmonia",
      "price": 12,
      "alergenos": "no conté"
    },
    {
      "title": "penicillin",
      "description": "dewar's white label whiskey, te de lapsang, gingebre & llimona",
      "flavors": "només amb recepta",
      "price": 11,
      "al·lèrgens": "no conté"
    }
  ],
  "cocktailSinAlcohol": [
    {
      "title": "sober october",
      "price": "8.5",
      "description": "martini floreale, gingebre, llimona i soda",
      "alergenos": "no conté"
    },
    {
      "title": "i don't remember november",
      "price": "8.5",
      "description": "martini floreale, alfàbrega, llimona i soda",
      "alergenos": "no conté"
    }
  ],
  "vinosNaturales": [
    {
      "title": "la figa",
      "description": "negre, lleuger i fresc, de garnatxa i carinyena de pau i rabós.",
      "price": {
        "copa": "5.5",
        "botella": "30"
      },
      "al·lèrgens": "conté sulfits"
    },
    {
      "title": "panorama",
      "description": "blanc de limoux, lleuger, aromàtic i molt agradable al paladar, omple sense embafar.",
      "price": {
        "copa": "5.5",
        "botella": "30"
      },
      "al·lèrgens": "conté sulfits"
    },
    {
      "title": "mandarines",
      "description": "orange de garnatxa blanca derrapada.",
      "price": {
        "copa": "7.5",
        "botella": "40"
      },
      "al·lèrgens": "conté sulfits"
    },
    {
      "title": "blublub",
      "description": "espumós d'una sola fermentació, xarel.lo 100% de la família ros marina en font-rubí, penedés.",
      "price": {
        "copa": "5.5",
        "botella": "30"
      },
      "al·lèrgens": "conté sulfits"
    }
  ],
  "vinsJerez": [
    {
      "title": "fino los amigos",
      "price": "3",
      "description": "sec i lleuger, (15%)",
      "alergenos": "conté sulfits"
    },
    {
      "title": "fino 10 gran barquero",
      "price": "4",
      "description": "frescor, elegància i complexitat, (15%)",
      "alergenos": "conté sulfits"
    },
    {
      "title": "fino 10 rama gran barquero",
      "price": "6.5",
      "description": "intens, harmònic i fresc, (15%)",
      "alergenos": "conté sulfits"
    },
    {
      "title": "amontillado 25 gran barquero",
      "price": "6.5",
      "description": "elegant i complex, (19%)",
      "alergenos": "conté sulfits"
    },
    {
      "title": "oloroso 25 gran barquero",
      "price": "6.5",
      "description": "intens, penetrant, ple de matisos, (19%)",
      "alergenos": "conté sulfits"
    }
  ],
  "ginTonic": [
    {
      "title": "bobombay dry",
      "price": "11",
      "alergenos": "no conté"
    },
    {
      "title": "bobombay sapphire",
      "price": "11",
      "alergenos": "no conté"
    },
    {
      "title": "bobombay cru",
      "price": "12",
      "alergenos": "no conté"
    },
    {
      "title": "corpen mestral",
      "price": "12",
      "alergenos": "no conté"
    },
    {
      "title": "condesa",
      "price": "12",
      "alergenos": "no conté"
    },
    {
      "title": "100&nomore",
      "price": "13",
      "alergenos": "no contiene"
    },
    {
      "title": "bes gin",
      "price": "12",
      "alergenos": "no conté"
    }
  ],
  "whisky": [
    {
      "title": "dewar's 12",
      "price": "9",
      "alergenos": "no conté"
    },
    {
      "title": "dewar's 15",
      "price": "10",
      "alergenos": "no conté"
    },
    {
      "title": "glenlivet founders reserve",
      "price": "10",
      "alergenos": "no conté"
    },
    {
      "title": "glenlivet 12",
      "price": "10",
      "alergenos": "no conté"
    },
    {
      "title": "tenjaku blend",
      "price": "8",
      "alergenos": "no conté"
    },
    {
      "title": "tenjaku pure malt",
      "price": "10",
      "alergenos": "no conté"
    },
    {
      "title": "laphroaig 10",
      "price": "10",
      "alergenos": "no conté"
    },
    {
      "title": "michter's bourbon",
      "price": "12",
      "alergenos": "no conté"
    },
    {
      "title": "michter's rye bourbon",
      "price": "12",
      "alergenos": "no conté"
    },
    {
      "title": "woodford reserve",
      "price": "10",
      "alergenos": "no conté"
    },
    {
      "title": "woodford reserve rye",
      "price": "10",
      "alergenos": "no conté"
    },
    {
      "title": "sazerac rye",
      "price": "10",
      "alergenos": "no conté"
    }
  ],
  "rones": [
    {
      "title": "santa teresa añejo",
      "price": "8",
      "alergenos": "no conté"
    },
    {
      "title": "santa teresa 1796",
      "price": "10",
      "alergenos": "no conté"
    },
    {
      "title": "havanna 7",
      "price": "8",
      "alergenos": "no conté"
    },
    {
      "title": "diplomatico",
      "price": "10",
      "alergenos": "no conté"
    },
    {
      "title": "plantation xo",
      "price": "12",
      "alergenos": "no conté"
    },
    {
      "title": "santiago de cuba",
      "price": "8",
      "alergenos": "no conté"
    }
  ],
  "agaves": [
    {
      "title": "mezcal union viejo",
      "price": "14",
      "description": "agave espadín i tobala, mantega i canyella",
      "alergenos": "no conté"
    },
    {
      "title": "mezcal union uno",
      "price": "10",
      "description": "agave espadín i cirial, equilibrat i cítric",
      "alergenos": "no conté"
    },
    {
      "title": "mezcal koch elemental",
      "price": "10",
      "description": "agave espadín, fruites madures i un toc d'herbes",
      "alergenos": "no conté"
    },
    {
      "title": "mezcal ojo de tigre",
      "price": "8",
      "description": "agave espadín i tobala, caramel i un toc de fruits secs",
      "alergenos": "no conté"
    },
    {
      "title": "mezcal derrumbres durango",
      "price": "11",
      "description": "agave cenizo, fruits d'estiu, nous i notes minerals",
      "alergenos": "no conté"
    },
    {
      "title": "tequila patron silver",
      "price": "10",
      "alergenos": "no conté"
    },
    {
      "title": "tequila patron añejo",
      "price": "16",
      "alergenos": "no conté"
    },
    {
      "title": "tequila cazadores blanco",
      "price": "8",
      "alergenos": "no conté"
    },
    {
      "title": "tequila cazadores reposado",
      "price": "8",
      "alergenos": "no conté"
    },
    {
      "title": "tequila 7 leguas blanco",
      "price": "13",
      "alergenos": "no conté"
    },
    {
      "title": "tequila arette blanco",
      "price": "10",
      "alergenos": "no conté"
    }
  ],
  "vodkas": [
    {
      "title": "grey goose",
      "price": "11",
      "alergenos": "no conté"
    },
    {
      "title": "eristoff",
      "price": "8",
      "alergenos": "no contiene"
    },
    {
      "title": "koskenkorva",
      "price": "8",
      "alergenos": "no conté"
    }
  ],
  "vermut": [
    {
      "title": "martini rosso / bianco",
      "price": "3.5",
      "alergenos": "no conté"
    },
    {
      "title": "martini rubino / ambrato",
      "price": "4.5",
      "alergenos": "no conté"
    },
    {
      "title": "cocchi rosa",
      "price": "6.5",
      "alergenos": "no conté"
    },
    {
      "title": "cocchi americano",
      "price": "6.5",
      "alergenos": "no conté"
    },
    {
      "title": "cocchi di torino",
      "price": "6",
      "alergenos": "no conté"
    },
    {
      "title": "cocchi dopo teatro",
      "price": "7.5",
      "alergenos": "no conté"
    }
  ],
  "cervezas": [
    {
      "title": "almogàver vicious ipa",
      "price": "4.6",
      "al·lèrgens": "no conté"
    },
    {
      "title": "almogàver txiringuito sour",
      "price": "4.6",
      "al·lèrgens": "conté gluten"
    },
    {
      "title": "estrella galicia",
      "price": "3,5",
      "al·lèrgens": "conté gluten"
    }
  ],
  "comida": [
    {
      "title": "pataton bloody mary",
      "price": "2.5",
      "al·lèrgens": "conté api"
    },
    {
      "title": "olives tutti frutti",
      "price": "3.5",
      "al·lèrgens": "no conté"
    },
    {
      "title": "gildas d`anxova",
      "price": "5",
      "al·lèrgens": "conté peix"
    }
  ]
}
